odoo/addons/product_dimension/README.rst
odoo/addons/product_dimension/__init__.py
odoo/addons/product_dimension/__manifest__.py
odoo/addons/product_dimension/i18n/ca.po
odoo/addons/product_dimension/i18n/de.po
odoo/addons/product_dimension/i18n/es.po
odoo/addons/product_dimension/i18n/fr.po
odoo/addons/product_dimension/i18n/fr_FR.po
odoo/addons/product_dimension/i18n/product_dimension.pot
odoo/addons/product_dimension/i18n/pt.po
odoo/addons/product_dimension/i18n/pt_BR.po
odoo/addons/product_dimension/i18n/sl.po
odoo/addons/product_dimension/migrations/12.0.2.0.0/pre-migration.py
odoo/addons/product_dimension/models/__init__.py
odoo/addons/product_dimension/models/product.py
odoo/addons/product_dimension/readme/CONTRIBUTORS.rst
odoo/addons/product_dimension/readme/DESCRIPTION.rst
odoo/addons/product_dimension/readme/USAGE.rst
odoo/addons/product_dimension/static/description/icon.png
odoo/addons/product_dimension/static/description/index.html
odoo/addons/product_dimension/tests/__init__.py
odoo/addons/product_dimension/tests/test_compute_volume.py
odoo/addons/product_dimension/views/product_view.xml
odoo12_addon_product_dimension-12.0.3.0.0.dist-info/METADATA
odoo12_addon_product_dimension-12.0.3.0.0.dist-info/WHEEL
odoo12_addon_product_dimension-12.0.3.0.0.dist-info/top_level.txt
odoo12_addon_product_dimension-12.0.3.0.0.dist-info/RECORD
