Metadata-Version: 2.1
Name: odoo12-addon-product-dimension
Version: 12.0.3.0.0
Summary: Product Dimension
Home-page: https://github.com/OCA/product-attribute
Author: brain-tec AG, ADHOC SA, Camptocamp SA, Odoo Community Association (OCA)
Author-email: support@odoo-community.org
License: AGPL-3
Platform: UNKNOWN
Classifier: Programming Language :: Python
Classifier: Framework :: Odoo
Classifier: License :: OSI Approved :: GNU Affero General Public License v3
Requires-Python: >=3.5
Requires-Dist: odoo12-addon-product-logistics-uom
Requires-Dist: odoo (<12.1dev,>=12.0a)
